timezone_handler.py
timezone_handler-0.0.1.dist-info/LICENSE.txt
timezone_handler-0.0.1.dist-info/METADATA
timezone_handler-0.0.1.dist-info/WHEEL
timezone_handler-0.0.1.dist-info/top_level.txt
timezone_handler-0.0.1.dist-info/RECORD
