Metadata-Version: 2.1
Name: timezone_handler
Version: 0.0.1
Summary: This Package designed to handle the DST(Day Light Savings)
Author-email: Rahul Pandey <rahulpandey.python81@gmail.com>
Classifier: Programming Language :: Python :: 3
Classifier: License :: OSI Approved :: MIT License
Classifier: Operating System :: OS Independent
Requires-Python: >=3.7
License-File: LICENSE.txt
